iztro_py/__init__.py
iztro_py/astro/__init__.py
iztro_py/astro/astro.py
iztro_py/astro/functional_astrolabe.py
iztro_py/astro/functional_palace.py
iztro_py/astro/functional_star.py
iztro_py/astro/functional_surpalaces.py
iztro_py/astro/horoscope.py
iztro_py/astro/palace.py
iztro_py/data/__init__.py
iztro_py/data/brightness.py
iztro_py/data/constants.py
iztro_py/data/earthly_branches.py
iztro_py/data/heavenly_stems.py
iztro_py/data/types.py
iztro_py/i18n/__init__.py
iztro_py/i18n/locales/__init__.py
iztro_py/i18n/locales/en_US.py
iztro_py/i18n/locales/ja_JP.py
iztro_py/i18n/locales/ko_KR.py
iztro_py/i18n/locales/vi_VN.py
iztro_py/i18n/locales/zh_CN.py
iztro_py/i18n/locales/zh_TW.py
iztro_py/star/__init__.py
iztro_py/star/location.py
iztro_py/star/major_star.py
iztro_py/star/minor_star.py
iztro_py/star/mutagen.py
iztro_py/utils/__init__.py
iztro_py/utils/calendar.py
iztro_py/utils/helpers.py
iztro_py-0.3.2.dist-info/licenses/LICENSE
iztro_py-0.3.2.dist-info/METADATA
iztro_py-0.3.2.dist-info/WHEEL
iztro_py-0.3.2.dist-info/top_level.txt
iztro_py-0.3.2.dist-info/RECORD
