Metadata-Version: 2.4
Name: iztro-py
Version: 0.3.2
Summary: A pure Python implementation of iztro - A lightweight Zi Wei Dou Shu (Purple Star Astrology) library with full i18n support (6 languages)
Author: iztro-py Contributors
Project-URL: Homepage, https://github.com/spyfree/iztro-py
Project-URL: Documentation, https://github.com/spyfree/iztro-py#readme
Project-URL: Repository, https://github.com/spyfree/iztro-py
Project-URL: Issues, https://github.com/spyfree/iztro-py/issues
Keywords: astrology,ziwei,ziweidoushu,purple-star,chinese-astrology
Classifier: Development Status :: 4 - Beta
Classifier: Intended Audience :: Developers
Classifier: License :: OSI Approved :: MIT License
Classifier: Programming Language :: Python :: 3
Classifier: Programming Language :: Python :: 3.8
Classifier: Programming Language :: Python :: 3.9
Classifier: Programming Language :: Python :: 3.10
Classifier: Programming Language :: Python :: 3.11
Classifier: Programming Language :: Python :: 3.12
Classifier: Topic :: Software Development :: Libraries :: Python Modules
Requires-Python: >=3.8
License-File: LICENSE
Requires-Dist: pydantic>=2.0.0
Requires-Dist: python-dateutil>=2.8.0
Requires-Dist: lunarcalendar>=0.0.9
Provides-Extra: dev
Requires-Dist: pytest>=7.0.0; extra == "dev"
Requires-Dist: pytest-cov>=4.0.0; extra == "dev"
Requires-Dist: black>=23.0.0; extra == "dev"
Requires-Dist: mypy>=1.0.0; extra == "dev"
Requires-Dist: ruff>=0.1.0; extra == "dev"
Dynamic: license-file
